{
    "sitemap": {
        "layout": false
    },

    "branding": {
        "title": "Branding"
    },

    "community-download": {
        "title": "Download Handsontable Community Edition"
    },

    "developers": {
        "title": "Developers Hub"
    },

    "download": {
        "title": "Download"
    },

    "knowledge-base": {
        "title": "Knowledge base"
    },

    "pro-download": {
        "title": "Download Handsontable Pro"
    },

    "terms-of-use": {
        "title": "Terms of use"
    },

    "examples": {
        "title": "Examples"
    },

    "features": {
        "title": "Features"
    },

    "index": {
        "title": "JavaScript Spreadsheet Library For Web Apps"
    },

    "pricing": {
        "title": "Pricing plans"
    },

    "support": {
        "title": "Priority support and consulting services"
    },

    "team": {
        "title": "Our team"
    },

    "contact": {
        "title": "Get nn touch"
    },

    "privacy": {
        "title": "Privacy policy"
    },

    "resellers": {
        "title": "Resellers"
    },

    "404": {
        "title": "Page not found"
    }
}